sceneprogsyn/__init__.py
sceneprogsyn/debugger.py
sceneprogsyn/progsyn.py
sceneprogsyn-0.1.0.dist-info/METADATA
sceneprogsyn-0.1.0.dist-info/WHEEL
sceneprogsyn-0.1.0.dist-info/top_level.txt
sceneprogsyn-0.1.0.dist-info/RECORD
