Metadata-Version: 2.4
Name: sceneprogsyn
Version: 0.1.0
Summary: An LLM based program synthesizer for custom DSLs
Home-page: https://github.com/KunalMGupta/sceneprogsyn.git
Author: Kunal Gupta
Author-email: k5upta@ucsd.edu
Classifier: Programming Language :: Python :: 3
Classifier: License :: OSI Approved :: MIT License
Classifier: Operating System :: OS Independent
Requires-Python: >=3.11
Requires-Dist: sceneprogllm
Dynamic: author
Dynamic: author-email
Dynamic: classifier
Dynamic: description
Dynamic: description-content-type
Dynamic: home-page
Dynamic: requires-dist
Dynamic: requires-python
Dynamic: summary
